xyz/__init__.py
xyz/algorithms/__init__.py
xyz/algorithms/synthesis/__init__.py
xyz/algorithms/synthesis/_cardinality_reduction.py
xyz/algorithms/synthesis/_exact_cnot_synthesis.py
xyz/algorithms/synthesis/_ground_state_calibration.py
xyz/algorithms/synthesis/_heuristic_cnot_synthesis.py
xyz/algorithms/synthesis/_qubit_decomposition.py
xyz/algorithms/synthesis/_qubit_reduction.py
xyz/algorithms/synthesis/_support_reduction.py
xyz/algorithms/synthesis/library_cnot_synthesis.py
xyz/algorithms/synthesis/prepare_state.py
xyz/algorithms/synthesis/library/__init__.py
xyz/algorithms/synthesis/library/default_library.py
xyz/algorithms/synthesis/library/library.py
xyz/algorithms/verification/__init__.py
xyz/algorithms/verification/diff_states.py
xyz/algorithms/verification/verify_circuit.py
xyz/boolean/__init__.py
xyz/boolean/sum_of_product.py
xyz/boolean/truth_table.py
xyz/circuit/__init__.py
xyz/circuit/_mapping.py
xyz/circuit/_optimization.py
xyz/circuit/_qiskit.py
xyz/circuit/qcircuit.py
xyz/circuit/basic_gates/__init__.py
xyz/circuit/basic_gates/crx.py
xyz/circuit/basic_gates/cry.py
xyz/circuit/basic_gates/crz.py
xyz/circuit/basic_gates/cu.py
xyz/circuit/basic_gates/cx.py
xyz/circuit/basic_gates/mcmy.py
xyz/circuit/basic_gates/mcry.py
xyz/circuit/basic_gates/muxy.py
xyz/circuit/basic_gates/rx.py
xyz/circuit/basic_gates/ry.py
xyz/circuit/basic_gates/rz.py
xyz/circuit/basic_gates/u.py
xyz/circuit/basic_gates/x.py
xyz/circuit/basic_gates/z.py
xyz/circuit/basic_gates/base/__init__.py
xyz/circuit/basic_gates/base/control.py
xyz/circuit/basic_gates/base/gate.py
xyz/circuit/basic_gates/base/qubit.py
xyz/circuit/basic_gates/base/rotation.py
xyz/circuit/basic_gates/base/unitary.py
xyz/circuit/decomposition/__init__.py
xyz/circuit/decomposition/decompose_mcry.py
xyz/circuit/super_gates/__init__.py
xyz/circuit/super_gates/special_gates.py
xyz/io/__init__.py
xyz/io/write_blif.py
xyz/network/__init__.py
xyz/network/network.py
xyz/operator/__init__.py
xyz/operator/control.py
quantum_xyz-0.1.1.dist-info/METADATA
quantum_xyz-0.1.1.dist-info/WHEEL
quantum_xyz-0.1.1.dist-info/top_level.txt
quantum_xyz-0.1.1.dist-info/RECORD
