Metadata-Version: 2.1
Name: quantum-xyz
Version: 0.1.1
Summary: A quantum circuit synthesis library
Author: Hanyu Wang
Project-URL: Documentation, https://quantum-xyz.readthedocs.io/en/latest/
Project-URL: Repository, https://github.com/Nozidoali/quantum-xyz.git
Keywords: quantum computing,eda
Classifier: Programming Language :: Python :: 3
Classifier: Operating System :: OS Independent
Requires-Python: >=3.10
Requires-Dist: llist ==0.7.1
Requires-Dist: matplotlib ==3.7.1
Requires-Dist: numpy ==1.23.5
Requires-Dist: qiskit ==0.43.1
Requires-Dist: qiskit-ibmq-provider ==0.20.2
Requires-Dist: qiskit-terra ==0.24.1
Requires-Dist: scipy ==1.10.1
